setup.cfg
setup.py
odlemrecon/__init__.py
odlemrecon/emreconoperators.py
odlemrecon/util.py
odlemrecon.egg-info/PKG-INFO
odlemrecon.egg-info/SOURCES.txt
odlemrecon.egg-info/dependency_links.txt
odlemrecon.egg-info/requires.txt
odlemrecon.egg-info/top_level.txt